{"@context":{"@language":"en","@vocab":"https://schema.org/","citeAs":"cr:citeAs","column":"cr:column","conformsTo":"dct:conformsTo","cr":"http://mlcommons.org/croissant/","data":{"@id":"cr:data","@type":"@json"},"dataBiases":"cr:dataBiases","dataCollection":"cr:dataCollection","dataType":{"@id":"cr:dataType","@type":"@vocab"},"dct":"http://purl.org/dc/terms/","extract":"cr:extract","field":"cr:field","fileProperty":"cr:fileProperty","fileObject":"cr:fileObject","fileSet":"cr:fileSet","format":"cr:format","includes":"cr:includes","isEnumeration":"cr:isEnumeration","jsonPath":"cr:jsonPath","key":"cr:key","md5":"cr:md5","parentField":"cr:parentField","path":"cr:path","personalSensitiveInformation":"cr:personalSensitiveInformation","recordSet":"cr:recordSet","references":"cr:references","regex":"cr:regex","repeated":"cr:repeated","replace":"cr:replace","sc":"https://schema.org/","separator":"cr:separator","source":"cr:source","subField":"cr:subField","transform":"cr:transform","wd":"https://www.wikidata.org/wiki/"},"alternateName":"Internet of Things (IoT)","conformsTo":"http://mlcommons.org/croissant/1.0","license":{"@type":"sc:CreativeWork","name":"Unknown"},"distribution":[{"contentUrl":"https://www.kaggle.com/api/v1/datasets/download/taranvee/smart-home-dataset-with-weather-information?datasetVersionNumber=1","contentSize":"19.429 MB","md5":"CEoF5t3rTobF05y8Vtwg9w==","encodingFormat":"application/zip","@id":"archive.zip","@type":"cr:FileObject","name":"archive.zip","description":"Archive containing all the contents of the Smart Home Dataset with weather Information dataset"},{"contentUrl":"HomeC.csv","containedIn":{"@id":"archive.zip"},"encodingFormat":"text/csv","@id":"HomeC.csv_fileobject","@type":"cr:FileObject","name":"HomeC.csv","description":"This CSV file contains the readings with a time span of 1 minute OF 350 DAYS of house appliances in kW from a smart meter and weather conditions of that particular region."}],"recordSet":[{"field":[{"dataType":["sc:Integer"],"source":{"fileObject":{"@id":"HomeC.csv_fileobject"},"extract":{"column":"time"}},"@id":"HomeC.csv/time","@type":"cr:Field","name":"time","description":"time"},{"dataType":["sc:Float"],"source":{"fileObject":{"@id":"HomeC.csv_fileobject"},"extract":{"column":"use [kW]"}},"@id":"HomeC.csv/use\u002B%5BkW%5D","@type":"cr:Field","name":"use [kW]","description":"Total energy consumption"},{"dataType":["sc:Float"],"source":{"fileObject":{"@id":"HomeC.csv_fileobject"},"extract":{"column":"gen [kW]"}},"@id":"HomeC.csv/gen\u002B%5BkW%5D","@type":"cr:Field","name":"gen [kW]","description":"Total energy generated by means of solar or other power generation resources"},{"dataType":["sc:Float"],"source":{"fileObject":{"@id":"HomeC.csv_fileobject"},"extract":{"column":"House overall [kW]"}},"@id":"HomeC.csv/House\u002Boverall\u002B%5BkW%5D","@type":"cr:Field","name":"House overall [kW]","description":"overall house energy consumption"},{"dataType":["sc:Float"],"source":{"fileObject":{"@id":"HomeC.csv_fileobject"},"extract":{"column":"Dishwasher [kW]"}},"@id":"HomeC.csv/Dishwasher\u002B%5BkW%5D","@type":"cr:Field","name":"Dishwasher [kW]","description":"energy consumed by specific appliance"},{"dataType":["sc:Float"],"source":{"fileObject":{"@id":"HomeC.csv_fileobject"},"extract":{"column":"Furnace 1 [kW]"}},"@id":"HomeC.csv/Furnace\u002B1\u002B%5BkW%5D","@type":"cr:Field","name":"Furnace 1 [kW]","description":"energy consumed by specific appliance"},{"dataType":["sc:Float"],"source":{"fileObject":{"@id":"HomeC.csv_fileobject"},"extract":{"column":"Furnace 2 [kW]"}},"@id":"HomeC.csv/Furnace\u002B2\u002B%5BkW%5D","@type":"cr:Field","name":"Furnace 2 [kW]","description":"energy consumed by specific appliance"},{"dataType":["sc:Float"],"source":{"fileObject":{"@id":"HomeC.csv_fileobject"},"extract":{"column":"Home office [kW]"}},"@id":"HomeC.csv/Home\u002Boffice\u002B%5BkW%5D","@type":"cr:Field","name":"Home office [kW]","description":"energy consumed by specific appliance"},{"dataType":["sc:Float"],"source":{"fileObject":{"@id":"HomeC.csv_fileobject"},"extract":{"column":"Fridge [kW]"}},"@id":"HomeC.csv/Fridge\u002B%5BkW%5D","@type":"cr:Field","name":"Fridge [kW]","description":"energy consumed by specific appliance"},{"dataType":["sc:Float"],"source":{"fileObject":{"@id":"HomeC.csv_fileobject"},"extract":{"column":"Wine cellar [kW]"}},"@id":"HomeC.csv/Wine\u002Bcellar\u002B%5BkW%5D","@type":"cr:Field","name":"Wine cellar [kW]","description":"energy consumed by specific appliance"},{"dataType":["sc:Float"],"source":{"fileObject":{"@id":"HomeC.csv_fileobject"},"extract":{"column":"Garage door [kW]"}},"@id":"HomeC.csv/Garage\u002Bdoor\u002B%5BkW%5D","@type":"cr:Field","name":"Garage door [kW]","description":"energy consumed by specific appliance"},{"dataType":["sc:Float"],"source":{"fileObject":{"@id":"HomeC.csv_fileobject"},"extract":{"column":"Kitchen 12 [kW]"}},"@id":"HomeC.csv/Kitchen\u002B12\u002B%5BkW%5D","@type":"cr:Field","name":"Kitchen 12 [kW]","description":"energy consumption in kitchen 1"},{"dataType":["sc:Float"],"source":{"fileObject":{"@id":"HomeC.csv_fileobject"},"extract":{"column":"Kitchen 14 [kW]"}},"@id":"HomeC.csv/Kitchen\u002B14\u002B%5BkW%5D","@type":"cr:Field","name":"Kitchen 14 [kW]","description":"energy consumption in kitchen 2"},{"dataType":["sc:Float"],"source":{"fileObject":{"@id":"HomeC.csv_fileobject"},"extract":{"column":"Kitchen 38 [kW]"}},"@id":"HomeC.csv/Kitchen\u002B38\u002B%5BkW%5D","@type":"cr:Field","name":"Kitchen 38 [kW]","description":"energy consumption in kitchen 3"},{"dataType":["sc:Float"],"source":{"fileObject":{"@id":"HomeC.csv_fileobject"},"extract":{"column":"Barn [kW]"}},"@id":"HomeC.csv/Barn\u002B%5BkW%5D","@type":"cr:Field","name":"Barn [kW]","description":"energy consumed by specific appliance"},{"dataType":["sc:Float"],"source":{"fileObject":{"@id":"HomeC.csv_fileobject"},"extract":{"column":"Well [kW]"}},"@id":"HomeC.csv/Well\u002B%5BkW%5D","@type":"cr:Field","name":"Well [kW]","description":"energy consumed by specific appliance"},{"dataType":["sc:Float"],"source":{"fileObject":{"@id":"HomeC.csv_fileobject"},"extract":{"column":"Microwave [kW]"}},"@id":"HomeC.csv/Microwave\u002B%5BkW%5D","@type":"cr:Field","name":"Microwave [kW]","description":"energy consumed by specific appliance"},{"dataType":["sc:Float"],"source":{"fileObject":{"@id":"HomeC.csv_fileobject"},"extract":{"column":"Living room [kW]"}},"@id":"HomeC.csv/Living\u002Broom\u002B%5BkW%5D","@type":"cr:Field","name":"Living room [kW]","description":"energy consumption in Living room"},{"dataType":["sc:Float"],"source":{"fileObject":{"@id":"HomeC.csv_fileobject"},"extract":{"column":"Solar [kW]"}},"@id":"HomeC.csv/Solar\u002B%5BkW%5D","@type":"cr:Field","name":"Solar [kW]","description":"Solar power generation"},{"dataType":["sc:Float"],"source":{"fileObject":{"@id":"HomeC.csv_fileobject"},"extract":{"column":"temperature"}},"@id":"HomeC.csv/temperature","@type":"cr:Field","name":"temperature","description":"temperature"},{"dataType":["sc:Text"],"source":{"fileObject":{"@id":"HomeC.csv_fileobject"},"extract":{"column":"icon"}},"@id":"HomeC.csv/icon","@type":"cr:Field","name":"icon","description":"overall weather condition"},{"dataType":["sc:Float"],"source":{"fileObject":{"@id":"HomeC.csv_fileobject"},"extract":{"column":"humidity"}},"@id":"HomeC.csv/humidity","@type":"cr:Field","name":"humidity","description":"humidity"},{"dataType":["sc:Float"],"source":{"fileObject":{"@id":"HomeC.csv_fileobject"},"extract":{"column":"visibility"}},"@id":"HomeC.csv/visibility","@type":"cr:Field","name":"visibility","description":"visibility"},{"dataType":["sc:Text"],"source":{"fileObject":{"@id":"HomeC.csv_fileobject"},"extract":{"column":"summary"}},"@id":"HomeC.csv/summary","@type":"cr:Field","name":"summary","description":"summarise weather"},{"dataType":["sc:Float"],"source":{"fileObject":{"@id":"HomeC.csv_fileobject"},"extract":{"column":"apparentTemperature"}},"@id":"HomeC.csv/apparentTemperature","@type":"cr:Field","name":"apparentTemperature","description":"apparent temperature"},{"dataType":["sc:Float"],"source":{"fileObject":{"@id":"HomeC.csv_fileobject"},"extract":{"column":"pressure"}},"@id":"HomeC.csv/pressure","@type":"cr:Field","name":"pressure","description":"pressure"},{"dataType":["sc:Float"],"source":{"fileObject":{"@id":"HomeC.csv_fileobject"},"extract":{"column":"windSpeed"}},"@id":"HomeC.csv/windSpeed","@type":"cr:Field","name":"windSpeed","description":"wind speed"},{"dataType":["sc:Text"],"source":{"fileObject":{"@id":"HomeC.csv_fileobject"},"extract":{"column":"cloudCover"}},"@id":"HomeC.csv/cloudCover","@type":"cr:Field","name":"cloudCover","description":"cloudcover"},{"dataType":["sc:Integer"],"source":{"fileObject":{"@id":"HomeC.csv_fileobject"},"extract":{"column":"windBearing"}},"@id":"HomeC.csv/windBearing","@type":"cr:Field","name":"windBearing","description":"windbearing"},{"dataType":["sc:Float"],"source":{"fileObject":{"@id":"HomeC.csv_fileobject"},"extract":{"column":"precipIntensity"}},"@id":"HomeC.csv/precipIntensity","@type":"cr:Field","name":"precipIntensity","description":"precipitation Intensity"},{"dataType":["sc:Float"],"source":{"fileObject":{"@id":"HomeC.csv_fileobject"},"extract":{"column":"dewPoint"}},"@id":"HomeC.csv/dewPoint","@type":"cr:Field","name":"dewPoint","description":"dew point"},{"dataType":["sc:Float"],"source":{"fileObject":{"@id":"HomeC.csv_fileobject"},"extract":{"column":"precipProbability"}},"@id":"HomeC.csv/precipProbability","@type":"cr:Field","name":"precipProbability","description":"precipitation probability"}],"@id":"HomeC.csv","@type":"cr:RecordSet","name":"HomeC.csv","description":"This CSV file contains the readings with a time span of 1 minute OF 350 DAYS of house appliances in kW from a smart meter and weather conditions of that particular region."}],"version":1,"keywords":["subject \u003E science and technology \u003E energy","technique \u003E time series analysis","subject \u003E science and technology \u003E energy \u003E electricity","subject \u003E science and technology \u003E electronics","subject \u003E science and technology \u003E energy \u003E renewable energy"],"isAccessibleForFree":true,"includedInDataCatalog":{"@type":"sc:DataCatalog","name":"Kaggle","url":"https://www.kaggle.com"},"creator":{"@type":"sc:Person","name":"Taranveer Singh Anttal","url":"/taranvee","image":"https://storage.googleapis.com/kaggle-avatars/thumbnails/920850-kg.jpeg"},"publisher":{"@type":"sc:Organization","name":"Kaggle","url":"https://www.kaggle.com/organizations/kaggle","image":"https://storage.googleapis.com/kaggle-organizations/4/thumbnail.png"},"thumbnailUrl":"https://storage.googleapis.com/kaggle-datasets-images/157890/361868/cb095a6ca2621f4491345126ba201bd1/dataset-card.jpeg?t=2019-04-06-00-46-56","dateModified":"2019-04-06T00:41:00.947","datePublished":"2019-04-06T00:41:00.947","@type":"sc:Dataset","name":"Smart Home Dataset with weather Information","url":"https://www.kaggle.com/datasets/taranvee/smart-home-dataset-with-weather-information/versions/1","description":"This CSV file contains the readings with a time span of 1 minute of house appliances in kW from a smart meter and weather conditions of that particular region."}